masonite/__init__.py
masonite/api/Api.py
masonite/api/__init__.py
masonite/api/authentication/AuthenticatesTokens.py
masonite/api/authentication/__init__.py
masonite/api/commands/APIInstallCommand.py
masonite/api/controllers/AuthenticationController.py
masonite/api/controllers/__init__.py
masonite/api/facades/Api.py
masonite/api/facades/__init__.py
masonite/api/guards/JWTGuard.py
masonite/api/guards/__init__.py
masonite/api/middleware/JWTAuthenticationMiddleware.py
masonite/api/middleware/__init__.py
masonite/api/providers/ApiProvider.py
masonite/api/providers/__init__.py
masonite/api/stubs/api.py
masonite/api/stubs/routes/api.py
masonite/auth/MustVerifyEmail.py
masonite/auth/Sign.py
masonite/auth/__init__.py
masonite/authentication/Auth.py
masonite/authentication/__init__.py
masonite/authentication/guards/TestGuard.py
masonite/authentication/guards/WebGuard.py
masonite/authentication/guards/__init__.py
masonite/authentication/models/__init__.py
masonite/authentication/models/authenticates.py
masonite/authorization/AuthorizationResponse.py
masonite/authorization/AuthorizesRequest.py
masonite/authorization/Gate.py
masonite/authorization/Policy.py
masonite/authorization/__init__.py
masonite/authorization/models/__init__.py
masonite/authorization/models/authorizes.py
masonite/broadcasting/Broadcast.py
masonite/broadcasting/CanBroadcast.py
masonite/broadcasting/Channel.py
masonite/broadcasting/PresenceChannel.py
masonite/broadcasting/PrivateChannel.py
masonite/broadcasting/__init__.py
masonite/broadcasting/controllers/BroadcastingController.py
masonite/broadcasting/controllers/__init__.py
masonite/broadcasting/drivers/PusherDriver.py
masonite/broadcasting/drivers/__init__.py
masonite/broadcasting/providers/BroadcastProvider.py
masonite/broadcasting/providers/__init__.py
masonite/cache/Cache.py
masonite/cache/__init__.py
masonite/cache/drivers/FileDriver.py
masonite/cache/drivers/MemcacheDriver.py
masonite/cache/drivers/RedisDriver.py
masonite/cache/drivers/__init__.py
masonite-4.17.4.dist-info/LICENSE
masonite-4.17.4.dist-info/METADATA
masonite-4.17.4.dist-info/WHEEL
masonite-4.17.4.dist-info/entry_points.txt
masonite-4.17.4.dist-info/top_level.txt
masonite-4.17.4.dist-info/RECORD
